ba_syx_aas_environment_component_client/__init__.py
ba_syx_aas_environment_component_client/api/__init__.py
ba_syx_aas_environment_component_client/api/asset_administration_shell_api/__init__.py
ba_syx_aas_environment_component_client/api/asset_administration_shell_api/delete_file_by_path.py
ba_syx_aas_environment_component_client/api/asset_administration_shell_api/get_file_by_path.py
ba_syx_aas_environment_component_client/api/asset_administration_shell_api/put_file_by_path.py
ba_syx_aas_environment_component_client/api/asset_administration_shell_repository_api/__init__.py
ba_syx_aas_environment_component_client/api/asset_administration_shell_repository_api/delete_asset_administration_shell_by_id.py
ba_syx_aas_environment_component_client/api/asset_administration_shell_repository_api/delete_submodel_reference_by_id_aas_repository.py
ba_syx_aas_environment_component_client/api/asset_administration_shell_repository_api/delete_thumbnail_aas_repository.py
ba_syx_aas_environment_component_client/api/asset_administration_shell_repository_api/get_all_asset_administration_shells.py
ba_syx_aas_environment_component_client/api/asset_administration_shell_repository_api/get_all_submodel_references_aas_repository.py
ba_syx_aas_environment_component_client/api/asset_administration_shell_repository_api/get_asset_administration_shell_by_id.py
ba_syx_aas_environment_component_client/api/asset_administration_shell_repository_api/get_asset_information_aas_repository.py
ba_syx_aas_environment_component_client/api/asset_administration_shell_repository_api/get_thumbnail_aas_repository.py
ba_syx_aas_environment_component_client/api/asset_administration_shell_repository_api/post_asset_administration_shell.py
ba_syx_aas_environment_component_client/api/asset_administration_shell_repository_api/post_submodel_reference_aas_repository.py
ba_syx_aas_environment_component_client/api/asset_administration_shell_repository_api/put_asset_administration_shell_by_id.py
ba_syx_aas_environment_component_client-2.0.dist-info/METADATA
ba_syx_aas_environment_component_client-2.0.dist-info/WHEEL
ba_syx_aas_environment_component_client-2.0.dist-info/RECORD
